PVAssess/__init__.py
PVAssess/cluster.py
PVAssess/descriptor_gen.py
PVAssess/input_generation.py
PVAssess/output_extraction.py
PVAssess/overpotential.py
PVAssess/regression.py
PVAssess/structure_generation.py
PVAssess-0.0.5.dist-info/METADATA
PVAssess-0.0.5.dist-info/WHEEL
PVAssess-0.0.5.dist-info/entry_points.txt
PVAssess-0.0.5.dist-info/top_level.txt
PVAssess-0.0.5.dist-info/RECORD
